pypushflow/AbstractActor.py
pypushflow/ErrorHandler.py
pypushflow/ForkActor.py
pypushflow/JoinActor.py
pypushflow/PythonActor.py
pypushflow/RequestStatus.py
pypushflow/RouterActor.py
pypushflow/StartActor.py
pypushflow/StopActor.py
pypushflow/Submodel.py
pypushflow/UtilsMongoDb.py
pypushflow/Workflow.py
pypushflow/__init__.py
pypushflow/version.py
pypushflow/addon/__init__.py
pypushflow/addon/classes.py
pypushflow/addon/utils.py
pypushflow/representation/__init__.py
pypushflow/representation/scheme/__init__.py
pypushflow/representation/scheme/json_parser.py
pypushflow/representation/scheme/link.py
pypushflow/representation/scheme/moml_parser.py
pypushflow/representation/scheme/node.py
pypushflow/representation/scheme/ows_parser.py
pypushflow/representation/scheme/parser.py
pypushflow/representation/scheme/scheme.py
pypushflow/test/TestWorkflow.py
pypushflow/test/__init__.py
pypushflow/test/pythonActor1.py
pypushflow/test/pythonActor2.py
pypushflow/test/pythonActorTest.py
pypushflow/test/pythonErrorHandlerTest.py
pypushflow/test/test_Actors.py
pypushflow/test/test_UtilsMongoDb.py
pypushflow/test/test_Workflows.py
pypushflow/test/test_representation.py
pypushflow/test/utils.py
pypushflow-0.1.0.dist-info/LICENSE
pypushflow-0.1.0.dist-info/METADATA
pypushflow-0.1.0.dist-info/WHEEL
pypushflow-0.1.0.dist-info/top_level.txt
pypushflow-0.1.0.dist-info/RECORD
